pacbar
