Metadata-Version: 1.1
Name: click-pacbar
Version: 0.1.2
Summary: Helper method to turn the click.progressbar into a Pacman!
Home-page: https://github.com/AngellusMortis/click-pacbar
Author: Christopher Bailey
Author-email: cbailey@mort.is
License: MIT license
Keywords: pacbar
Platform: UNKNOWN
Classifier: Development Status :: 2 - Pre-Alpha
Classifier: Intended Audience :: Developers
Classifier: License :: OSI Approved :: MIT License
Classifier: Natural Language :: English
Classifier: Programming Language :: Python :: 2
Classifier: Programming Language :: Python :: 2.7
Classifier: Programming Language :: Python :: 3
Classifier: Programming Language :: Python :: 3.4
Classifier: Programming Language :: Python :: 3.5
Classifier: Programming Language :: Python :: 3.6
